{
  "layout": "drain_address_to_16xint32_vector_map",
  "outputs": [
    {
      "drain_addr": 0,
      "global_row": 0,
      "global_col_base": 0,
      "vector": [
        1167458304,
        1167458304,
        1167458304,
        1167458304,
        1167458304,
        1167458304,
        1167458304,
        1167458304,
        1167458304,
        1167458304,
        1167458304,
        1167458304,
        1167458304,
        1167458304,
        1167458304,
        1167458304
      ]
    }
  ]
}